concrete_frontend-0.0.10-py3.9-nspkg.pth
concrete/frontend/__init__.py
concrete/frontend/file.py
concrete_frontend-0.0.10.dist-info/LICENSE
concrete_frontend-0.0.10.dist-info/METADATA
concrete_frontend-0.0.10.dist-info/WHEEL
concrete_frontend-0.0.10.dist-info/namespace_packages.txt
concrete_frontend-0.0.10.dist-info/top_level.txt
concrete_frontend-0.0.10.dist-info/RECORD
